CHANGES.txt
README.txt
bootstrap.py
buildout.cfg
setup.py
src/zope/__init__.py
src/zope.app.dav.egg-info/PKG-INFO
src/zope.app.dav.egg-info/SOURCES.txt
src/zope.app.dav.egg-info/dependency_links.txt
src/zope.app.dav.egg-info/namespace_packages.txt
src/zope.app.dav.egg-info/not-zip-safe
src/zope.app.dav.egg-info/requires.txt
src/zope.app.dav.egg-info/top_level.txt
src/zope/app/__init__.py
src/zope/app/dav/__init__.py
src/zope/app/dav/adapter.py
src/zope/app/dav/configure.zcml
src/zope/app/dav/dav-configure.zcml
src/zope/app/dav/dav-meta.zcml
src/zope/app/dav/ftesting.zcml
src/zope/app/dav/interfaces.py
src/zope/app/dav/meta.zcml
src/zope/app/dav/metaconfigure.py
src/zope/app/dav/metadirectives.py
src/zope/app/dav/mkcol.py
src/zope/app/dav/opaquenamespaces.py
src/zope/app/dav/propfind.py
src/zope/app/dav/proppatch.py
src/zope/app/dav/testing.py
src/zope/app/dav/widget.py
src/zope/app/dav/tests/__init__.py
src/zope/app/dav/tests/dav.py
src/zope/app/dav/tests/dav.zcml
src/zope/app/dav/tests/test_adapter.py
src/zope/app/dav/tests/test_directives.py
src/zope/app/dav/tests/test_doctests.py
src/zope/app/dav/tests/test_functional_mkcol.py
src/zope/app/dav/tests/test_functional_propfind.py
src/zope/app/dav/tests/test_functional_proppatch.py
src/zope/app/dav/tests/test_mkcol.py
src/zope/app/dav/tests/test_propfind.py
src/zope/app/dav/tests/test_proppatch.py
src/zope/app/dav/tests/unitfixtures.py